sweetrpg_client/__init__.py
sweetrpg_client/client.py
sweetrpg_client/constants.py
sweetrpg_client/exceptions.py
sweetrpg_client/helpers.py
sweetrpg_client/types/__init__.py
sweetrpg_client/types/registry.py
sweetrpg_client-0.0.57.dist-info/LICENSE
sweetrpg_client-0.0.57.dist-info/METADATA
sweetrpg_client-0.0.57.dist-info/WHEEL
sweetrpg_client-0.0.57.dist-info/entry_points.txt
sweetrpg_client-0.0.57.dist-info/top_level.txt
sweetrpg_client-0.0.57.dist-info/RECORD
