Metadata-Version: 2.1
Name: sweetrpg-client
Version: 0.0.57
Summary: UNKNOWN
Home-page: https://sweetrpg.com
Author: Paul Schifferer
Author-email: dm@sweetrpg.com
License: MIT
Project-URL: Documentation, https://sweetrpg.github.io/client
Platform: UNKNOWN
Classifier: Development Status :: 3 - Alpha
Classifier: Intended Audience :: Developers
Classifier: License :: OSI Approved :: MIT License
Classifier: Operating System :: OS Independent
Classifier: Programming Language :: Python
Classifier: Topic :: Software Development :: Libraries :: Python Modules
License-File: LICENSE
Requires-Dist: marshmallow (==3.14.1)
Requires-Dist: sweetrpg-model-core
Requires-Dist: sweetrpg-api-core
Requires-Dist: sweetrpg-library-objects
Requires-Dist: requests
Requires-Dist: jsonapi-client
